mini_fiction/__init__.py
mini_fiction/application.py
mini_fiction/captcha.py
mini_fiction/celery.py
mini_fiction/context_processors.py
mini_fiction/database.py
mini_fiction/dumpload.py
mini_fiction/hashers.py
mini_fiction/linters.py
mini_fiction/models.py
mini_fiction/ponydump.py
mini_fiction/settings.py
mini_fiction/sphinx.conf
mini_fiction/tasks.py
mini_fiction/widgets.py
mini_fiction/apis/__init__.py
mini_fiction/apis/amsphinxql.py
mini_fiction/bl/__init__.py
mini_fiction/bl/adminlog.py
mini_fiction/bl/authors.py
mini_fiction/bl/commentable.py
mini_fiction/bl/comments.py
mini_fiction/bl/htmlblocks.py
mini_fiction/bl/logopics.py
mini_fiction/bl/news.py
mini_fiction/bl/registry.py
mini_fiction/bl/sorting.py
mini_fiction/bl/staticpages.py
mini_fiction/bl/stories.py
mini_fiction/bl/utils.py
mini_fiction/downloads/__init__.py
mini_fiction/downloads/base.py
mini_fiction/downloads/fb2.py
mini_fiction/downloads/html.py
mini_fiction/downloads/txt.py
mini_fiction/filters/__init__.py
mini_fiction/filters/base.py
mini_fiction/filters/typographus.py
mini_fiction/filters/fb2/__init__.py
mini_fiction/filters/fb2/fb2-description.xslt
mini_fiction/filters/fb2/html-to-fb2.xslt
mini_fiction/filters/fb2/join-fb2-docs.xslt
mini_fiction/filters/html/__init__.py
mini_fiction/filters/html/footnotes.xslt
mini_fiction/filters/html/post-normalize-html.xslt
mini_fiction/filters/html/pre-normalize-html.xslt
mini_fiction/fixtures/__init__.py
mini_fiction/fixtures/adminlogtype_dump.jsonl
mini_fiction/fixtures/author_dump.jsonl
mini_fiction/fixtures/htmlblock_dump.jsonl
mini_fiction/fixtures/rating_dump.jsonl
mini_fiction/fixtures/staticpage_dump.jsonl
mini_fiction/forms/__init__.py
mini_fiction/forms/author.py
mini_fiction/forms/chapter.py
mini_fiction/forms/comment.py
mini_fiction/forms/form.py
mini_fiction/forms/login.py
mini_fiction/forms/register.py
mini_fiction/forms/search.py
mini_fiction/forms/story.py
mini_fiction-0.0.4.dist-info/LICENSE.txt
mini_fiction-0.0.4.dist-info/METADATA
mini_fiction-0.0.4.dist-info/RECORD
mini_fiction-0.0.4.dist-info/WHEEL
mini_fiction-0.0.4.dist-info/entry_points.txt
mini_fiction-0.0.4.dist-info/top_level.txt
