Metadata-Version: 2.1
Name: mini-fiction
Version: 0.0.4
Summary: CMS for fanfics
Home-page: https://github.com/andreymal/mini_fiction
Author: andreymal
Author-email: andriyano-31@mail.ru
License: GPLv3
Project-URL: Bug Reports, https://github.com/andreymal/mini_fiction/issues
Platform: any
Classifier: Development Status :: 4 - Beta
Classifier: Framework :: Flask
Classifier: License :: OSI Approved
Classifier: License :: OSI Approved :: GNU General Public License v3 (GPLv3)
Classifier: Operating System :: OS Independent
Classifier: Programming Language :: Python
Classifier: Programming Language :: Python :: 3
Classifier: Programming Language :: Python :: 3.4
Classifier: Programming Language :: Python :: 3.5
Classifier: Programming Language :: Python :: 3.6
Classifier: Programming Language :: Python :: Implementation :: CPython
Classifier: Topic :: Internet :: WWW/HTTP :: WSGI
Classifier: Topic :: Internet :: WWW/HTTP :: WSGI :: Application
Requires-Python: >=3.4
Provides-Extra: full
Requires-Dist: Flask-WTF
Requires-Dist: Flask-Login (>=0.4.1)
Requires-Dist: Flask-Script
Requires-Dist: Flask-Babel
Requires-Dist: Flask (<1.0,>=0.12)
Requires-Dist: Cerberus (<1.2,>=1.0.1)
Requires-Dist: unidecode
Requires-Dist: python3-memcached
Requires-Dist: redis
Requires-Dist: celery (<5.0,>=4.0)
Requires-Dist: pony (>=0.7.2)
Requires-Dist: lxml
Provides-Extra: full
Requires-Dist: bcrypt; extra == 'full'
Requires-Dist: scrypt; extra == 'full'
Requires-Dist: mysqlclient; extra == 'full'
Requires-Dist: Pillow; extra == 'full'
Requires-Dist: diff-match-patch-python; extra == 'full'
Requires-Dist: captcha; extra == 'full'
